t8dev/__init__.py
t8dev/cpm.pt
t8dev/cpm.py
t8dev/path.pt
t8dev/path.py
t8dev/run.pt
t8dev/run.py
t8dev/cli/ascii2a2t.py
t8dev/cli/exits.py
t8dev/cli/mb6885.py
t8dev/cli/p2a2bin.py
t8dev/cli/wozmon_deposit.py
t8dev/cli/t8dev/__init__.py
t8dev/cli/t8dev/asl.py
t8dev/cli/t8dev/asx.py
t8dev/cli/t8dev/build.py
t8dev/cli/t8dev/emulator.pt
t8dev/cli/t8dev/isa.py
t8dev/cli/t8dev/main.py
t8dev/cli/t8dev/pytest.py
t8dev/cli/t8dev/shared.py
t8dev/cli/t8dev/toolset.py
t8dev/cli/t8dev/util.py
t8dev/cli/t8dev/emulator/__init__.py
t8dev/cli/t8dev/emulator/cscp.py
t8dev/cli/t8dev/emulator/other.py
t8dev/cli/t8dev/emulator/runcpm.py
t8dev/cli/t8dev/emulator/suite.py
t8dev/cli/t8dev/emulator/virtualt.py
t8dev/toolset/RunCPM.py
t8dev/toolset/VirtualT.py
t8dev/toolset/__init__.py
t8dev/toolset/asl.py
t8dev/toolset/asxxxx.py
t8dev/toolset/bm2.py
t8dev/toolset/cscp.py
t8dev/toolset/ctools.py
t8dev/toolset/disx.py
t8dev/toolset/dos33fs.py
t8dev/toolset/linapple.py
t8dev/toolset/osimg.py
t8dev/toolset/setup.py
t8dev-0.3.3.data/scripts/a1term
t8dev-0.3.3.data/scripts/a2printer
t8dev-0.3.3.data/scripts/charrom-vis
t8dev-0.3.3.data/scripts/cmpasl
t8dev-0.3.3.data/scripts/intel-disassm-clean
t8dev-0.3.3.data/scripts/t2a2dsk
t8dev-0.3.3.data/scripts/vlst
testmc/__init__.pt
testmc/__init__.py
testmc/conftest.py
testmc/midump.pt
testmc/midump.py
testmc/tmc.pt
testmc/tmc.py
testmc/generic/__init__.py
testmc/generic/iomem.pt
testmc/generic/iomem.py
testmc/generic/machine.pt
testmc/generic/machine.py
testmc/generic/mbytesio.pt
testmc/generic/mbytesio.py
testmc/generic/memory.pt
testmc/generic/memory.py
testmc/generic/registers.pt
testmc/generic/registers.py
testmc/i8080/__init__.pt
testmc/i8080/__init__.py
testmc/i8080/machine.pt
testmc/i8080/machine.py
testmc/i8080/nativetest.pt
testmc/i8080/opcodes.py
testmc/i8080/opimpl.pt
testmc/i8080/opimpl.py
testmc/i8080/bios/cpmcode.i80
testmc/i8080/programs/8080EX1.COM
testmc/i8080/programs/8080EX1.MAC
testmc/i8080/programs/8080PRE.COM
t8dev-0.3.3.dist-info/METADATA
t8dev-0.3.3.dist-info/WHEEL
t8dev-0.3.3.dist-info/entry_points.txt
t8dev-0.3.3.dist-info/top_level.txt
t8dev-0.3.3.dist-info/RECORD
