Metadata-Version: 2.4
Name: t8dev
Version: 0.3.3
Summary: Tools for 8-bit cross-development 
Author-email: "Curt J. Sampson" <cjs@cynic.net>
Project-URL: homepage, https://github.com/mc68-net/t8dev/tree/main/t8dev
Project-URL: source, https://github.com/mc68-net/t8dev
Project-URL: tracker, https://github.com/mc68-net/t8dev/issues
Requires-Python: >=3.9
Requires-Dist: r8format>=0.0.8
Requires-Dist: pytest
Requires-Dist: pytest_pt
Requires-Dist: requests
Requires-Dist: patool
Requires-Dist: py65
